MANIFEST.in
README.rst
setup.py
docs/HISTORY.txt
docs/LICENSE.GPL
docs/LICENSE.txt
ftw/__init__.py
ftw.dictstorage.egg-info/PKG-INFO
ftw.dictstorage.egg-info/SOURCES.txt
ftw.dictstorage.egg-info/dependency_links.txt
ftw.dictstorage.egg-info/entry_points.txt
ftw.dictstorage.egg-info/namespace_packages.txt
ftw.dictstorage.egg-info/not-zip-safe
ftw.dictstorage.egg-info/requires.txt
ftw.dictstorage.egg-info/top_level.txt
ftw/dictstorage/__init__.py
ftw/dictstorage/base.py
ftw/dictstorage/configure.zcml
ftw/dictstorage/interfaces.py
ftw/dictstorage/sql.py
ftw/dictstorage/testing.py
ftw/dictstorage/tests.py