Metadata-Version: 1.0
Name: ftw.dictstorage
Version: 1.2
Summary: Provides a layer for storing key / value paires.
Home-page: https://github.com/4teamwork/ftw.dictstorage/
Author: Rok Garbas
Author-email: mailto:info@4teamwork.ch
License: GPL2
Keywords: ftw key value storage sqlalchemy dictstorage
Platform: UNKNOWN
Classifier: Programming Language :: Python
Classifier: Topic :: Software Development :: Libraries :: Python Modules
